nnz/__init__.py
nnz/config.py
nnz/dataset.py
nnz/modeling.py
nnz/tools.py
nnz/workspace.py
nnz-0.0.2.dist-info/LICENCE
nnz-0.0.2.dist-info/METADATA
nnz-0.0.2.dist-info/WHEEL
nnz-0.0.2.dist-info/top_level.txt
nnz-0.0.2.dist-info/RECORD
