Metadata-Version: 2.1
Name: nnz
Version: 0.0.2
Summary: A small example package for datascience
Author-email: THULLIEZ Jeremy <j.thulliez@gmail.com>
Project-URL: Homepage, https://github.com/JeremZed/NN
Project-URL: Issues, https://github.com/JeremZed/NN/issues
Classifier: Programming Language :: Python :: 3
Classifier: License :: OSI Approved :: MIT License
Classifier: Operating System :: OS Independent
Requires-Python: >=3.12
License-File: LICENCE
Requires-Dist: keras
Requires-Dist: torch
Requires-Dist: matplotlib
Requires-Dist: scikit-learn
Requires-Dist: pandas
Requires-Dist: seaborn
